Lab1/blackbox.v
module blackbox(m, l, s, q);
    output m;
    input  l, s, q;
    wire   w04, w08, w09, w18, w20, w21, w22, w23, w27, w28, w29, w36, w42, w45, w50, w62, w79, w80, w84, w85, w92, w98, w99;
    or  o66(m, w79, w20, w23);
    and a56(w79, w29, w21, w62);
    not n10(w62, w98);
    and a76(w20, w21, w98, w29);
    and a65(w23, w80, w22);
    not n72(w80, w21);
    or  o93(w22, w50, w04);
    and a59(w50, w29, w98);
    and a94(w04, w18, w29);
    not n35(w18, w98);
    or  o88(w21, w85, w09);
    and a74(w85, w92, q);
    not n89(w92, l);
    and a54(w09, w42, l, s);
    not n15(w42, q);
    and a47(w98, w36, w28);
    not n2(w36, q);
    or  o32(w28, w99, w27);
    not n39(w99, s);
    not n26(w27, l);
    or  o61(w29, w08, w45, w84);
    not n70(w08, l);
    not n14(w45, s);
    not n58(w84, q);
endmodule // blackbox

Lab1/blackbox_tb.v
module blackbox_test;
reg l, s, q;                           // these are inputs to "circuit under test"
                                          // use "reg" not "wire" so can assign a value
wire m;                        // wires for the outputs of "circuit under test"

blackbox sc1 (m, l, s, q);  // the circuit under test

initial begin                             // initial = run at beginning of simulation
                                          // begin/end = associate block with initial

    $dumpfile("blackbox.vcd");                  // name of dump file to create
    $dumpvars(0,blackbox_test);                 // record all signals of module "sc_test" and sub-modules
                                          // remember to change "sc_test" to the correct
                                          // module name when writing your own test benches

    // test all four input combinations
    // remember that 2 inputs means 2^2 = 4 combinations
    // 3 inputs would mean 2^3 = 8 combinations to test, and so on
    // this is very similar to the input columns of a truth table
    l = 0; s = 0; q = 0; # 10;             // set initial values and wait 10 time units
    l = 0; s = 0; q = 1; # 10;             // change inputs and then wait 10 time units
    l = 0; s = 1; q = 0; # 10;               // as above
    l = 0; s = 1; q = 1; # 10;
    l = 1; s = 0; q = 0; # 10;
    l = 1; s = 0; q = 1; # 10;
    l = 1; s = 1; q = 0; # 10;
    l = 1; s = 1; q = 1; # 10;


    $finish;                              // end the simulation
end

initial
    $monitor("At time %2t, l = %d s = %d q = %d m = %d",
             $time, l, s, q, m);
endmodule // blackbox_test

Lab1/blackbox.vcd
$date
	Tue Jan 23 16:52:25 2018
$end
$version
	Icarus Verilog
$end
$timescale
	1s
$end
$scope module blackbox_test $end
$var wire 1 ! m $end
$var reg 1 " l $end
$var reg 1 # q $end
$var reg 1 $ s $end
$scope module sc1 $end
$var wire 1 " l $end
$var wire 1 ! m $end
$var wire 1 # q $end
$var wire 1 $ s $end
$var wire 1 % w04 $end
$var wire 1 & w08 $end
$var wire 1 ' w09 $end
$var wire 1 ( w18 $end
$var wire 1 ) w20 $end
$var wire 1 * w21 $end
$var wire 1 + w22 $end
$var wire 1 , w23 $end
$var wire 1 - w27 $end
$var wire 1 . w28 $end
$var wire 1 / w29 $end
$var wire 1 0 w36 $end
$var wire 1 1 w42 $end
$var wire 1 2 w45 $end
$var wire 1 3 w50 $end
$var wire 1 4 w62 $end
$var wire 1 5 w79 $end
$var wire 1 6 w80 $end
$var wire 1 7 w84 $end
$var wire 1 8 w85 $end
$var wire 1 9 w92 $end
$var wire 1 : w98 $end
$var wire 1 ; w99 $end
$upscope $end
$upscope $end
$enddefinitions $end
#0
$dumpvars
1;
1:
19
08
17
16
05
04
13
12
11
10
1/
1.
1-
1,
1+
0*
0)
0(
0'
1&
0%
0$
0#
0"
1!
$end
#10
0,
1%
1+
06
15
1(
03
14
1*
0:
18
01
00
07
1#
#20
1,
1!
0%
16
05
0(
13
04
0*
1:
08
11
10
17
0;
02
0#
1$
#30
0,
1%
1+
06
15
1(
03
14
1*
0:
18
01
00
07
1#
#40
1,
1!
0%
16
05
0(
13
04
0*
1:
08
11
10
17
1;
12
09
0-
0&
0#
0$
1"
#50
1!
1,
1%
1+
1(
03
14
0:
01
00
07
1#
#60
0,
06
15
1*
1'
0.
11
10
17
0;
02
0#
1$
#70
16
0+
0!
0*
0%
05
0'
0/
01
00
07
1#
