Lab3/mux.v
// output = A (when control == 0) or B (when control == 1)
module mux2(out, A, B, control);
    output out;
    input  A, B;
    input  control;
    wire   wA, wB, not_control;

    not n1(not_control, control);
    and a1(wA, A, not_control);
    and a2(wB, B, control);
    or  o1(out, wA, wB);
endmodule // mux2

// output = A (when control == 00) or B (when control == 01) or
//          C (when control == 10) or D (when control == 11)
module mux4(out, A, B, C, D, control);
    output      out;
    input       A, B, C, D;
    input [1:0] control;

    wire abo, cdo;

    mux2 ab (abo, A, B, control[0]);
    mux2 cd (cdo, C, D, control[0]);
    mux2 o (out, abo, cdo, control[1]);

endmodule // mux4

Lab3/logicunit.v
// 00 - AND, 01 - OR, 10 - NOR, 11 - XOR
module logicunit(out, A, B, control);
    output      out;
    input       A, B;
    input [1:0] control;
    wire a, o, no, xo;

    and a1(a, A, B);
    or o1(o, A, B);
    nor n1(no, A, B);
    xor x1(xo, A, B);

    mux4 r(out, a, o, no, xo, control);

endmodule // logicunit

Lab3/logicunit_tb.v
module logicunit_test;
    // exhaustively test your logic unit by adapting mux4_tb.v

    reg A = 0;
    always #1 A = !A;
    reg B = 0;
    always #2 B = !B;

    reg [1:0] control = 0;

    initial begin
        $dumpfile("logicunit.vcd");
        $dumpvars(0, logicunit_test);

        // control is initially 0
        # 4 control = 1; // wait 16 time units (why 16?) and then set it to 1
        # 4 control = 2; // wait 16 time units and then set it to 2
        # 4 control = 3; // wait 16 time units and then set it to 3
        # 4 $finish; // wait 16 time units and then end the simulation
    end

    wire out;
    logicunit l4(out, A, B, control);

    // you really should be using gtkwave instead
    /*
    initial begin
        $display("A B s o");
        $monitor("%d %d %d %d (at time %t)", A, B,, control, out, $time);
    end
    */
endmodule // logicunit_test

Lab3/logicunit.vcd
$date
	Sun Feb  4 16:12:24 2018
$end
$version
	Icarus Verilog
$end
$timescale
	1s
$end
$scope module logicunit_test $end
$var wire 1 ! out $end
$var reg 1 " A $end
$var reg 1 # B $end
$var reg 2 $ control [1:0] $end
$scope module l4 $end
$var wire 1 " A $end
$var wire 1 # B $end
$var wire 1 % a $end
$var wire 2 & control [1:0] $end
$var wire 1 ' no $end
$var wire 1 ( o $end
$var wire 1 ) xo $end
$var wire 1 ! out $end
$scope module r $end
$var wire 1 % A $end
$var wire 1 ( B $end
$var wire 1 ' C $end
$var wire 1 ) D $end
$var wire 2 * control [1:0] $end
$var wire 1 ! out $end
$var wire 1 + cdo $end
$var wire 1 , abo $end
$scope module ab $end
$var wire 1 % A $end
$var wire 1 ( B $end
$var wire 1 - control $end
$var wire 1 . not_control $end
$var wire 1 , out $end
$var wire 1 / wA $end
$var wire 1 0 wB $end
$upscope $end
$scope module cd $end
$var wire 1 ' A $end
$var wire 1 ) B $end
$var wire 1 1 control $end
$var wire 1 2 not_control $end
$var wire 1 + out $end
$var wire 1 3 wA $end
$var wire 1 4 wB $end
$upscope $end
$scope module o $end
$var wire 1 , A $end
$var wire 1 + B $end
$var wire 1 5 control $end
$var wire 1 6 not_control $end
$var wire 1 ! out $end
$var wire 1 7 wA $end
$var wire 1 8 wB $end
$upscope $end
$upscope $end
$upscope $end
$upscope $end
$enddefinitions $end
#0
$dumpvars
08
07
16
05
04
13
12
01
00
0/
1.
0-
0,
1+
b0 *
0)
0(
1'
b0 &
0%
b0 $
0#
0"
0!
$end
#1
0+
03
1(
0'
1)
1"
#2
0"
1#
#3
1!
17
1,
1/
1%
0)
1"
#4
0!
07
0,
0/
0.
02
0%
0(
1'
1-
11
0"
0#
b1 $
b1 &
b1 *
#5
1!
17
1,
1+
10
14
1(
0'
1)
1"
#6
0"
1#
#7
0+
04
1%
0)
1"
#8
18
1!
1+
0,
07
13
1.
00
12
06
0%
0(
1'
0-
01
15
0"
0#
b10 $
b10 &
b10 *
#9
0!
08
0+
03
1(
0'
1)
1"
#10
0"
1#
#11
1,
1/
1%
0)
1"
#12
0,
0/
0.
02
0%
0(
1'
1-
11
0"
0#
b11 $
b11 &
b11 *
#13
1!
18
1,
1+
10
14
1(
0'
1)
1"
#14
0"
1#
#15
0!
08
0+
04
1%
0)
1"
#16
0,
00
0%
0(
1'
0"
0#
